telaolparse/__init__.py
telaolparse/telaolparse.py
telaolparse/telaolparse_excel.py
telaolparse/telaolparse_forms.py
telaolparse/telaolparse_students.py
telaolparse-0.0.4.dist-info/METADATA
telaolparse-0.0.4.dist-info/WHEEL
telaolparse-0.0.4.dist-info/top_level.txt
telaolparse-0.0.4.dist-info/RECORD
