Metadata-Version: 2.1
Name: telaolparse
Version: 0.0.4
Summary: A library to parse Excel Files for TEL/AOL project
Home-page: https://github.com/telaolparse/homepage/
Author: Alexander Andreev
Author-email: andreyeffalex@gmail.com
License: UNKNOWN
Platform: UNKNOWN
Classifier: Programming Language :: Python :: 3.7
Requires-Dist: psycopg2
Requires-Dist: pandas
Requires-Dist: boto3
Requires-Dist: yandexcloud
Requires-Dist: yandex
